expiringdict/__init__.py
expiringdict_with_default-1.1.7.dist-info/METADATA
expiringdict_with_default-1.1.7.dist-info/RECORD
expiringdict_with_default-1.1.7.dist-info/WHEEL
expiringdict_with_default-1.1.7.dist-info/top_level.txt
expiringdict_with_default-1.1.7.dist-info/zip-safe
