Metadata-Version: 2.1
Name: expiringdict-with-default
Version: 1.1.7
Summary: Dictionary with auto-expiring values for caching purposes, support default value
Home-page: https://github.com/weaming/expiringdict
Author: weaming
Author-email: garden.yuen@gmail.com
License: Apache 2
Platform: UNKNOWN
Provides-Extra: test
Provides-Extra: test
Requires-Dist: nose; extra == 'test'
Requires-Dist: mock; extra == 'test'
Requires-Dist: coverage; extra == 'test'
